{"unfoldings":[{"id":1,"coords":[[0,0,0],[0,0,-1],[0,-1,-1],[0,-1,-2],[-1,-1,-2],[1,0,0],[1,0,1],[1,1,1]],"state":"SOLVED","solver":"Matt Parker","verifiers":["Stuart Ward","Octavia Togami","Andrea Consonni"]},{"id":2,"coords":[[0,0,0],[0,0,-1],[0,-1,-1],[0,-1,-2],[0,0,1],[-1,0,1],[-1,1,1],[1,0,0]],"state":"SOLVED","solver":"Georgios Papoutsis","verifiers":["Cyprien Heusse","Lewis Sugden","Lars Pos"]},{"id":3,"coords":[[0,0,0],[0,0,-1],[0,-1,-1],[-1,-1,-1],[0,0,-2],[1,0,0],[1,1,0],[1,1,1]],"state":"SOLVED","solver":"Samuel Lavis","verifiers":["Sullivan Figurskey","Rick Rijpers","Elise Baczek"]},{"id":4,"coords":[[0,0,0],[0,0,-1],[0,-1,-1],[0,-2,-1],[0,0,-2],[0,1,0],[-1,1,0],[1,0,0]],"state":"SOLVED","solver":"Viszmeg Krisztián","verifiers":["EbbDrop","Jonathan Burgess","Reed Pratt"]},{"id":5,"coords":[[0,0,0],[0,0,-1],[0,0,-2],[0,-1,-2],[0,0,1],[0,1,1],[-1,0,1],[1,0,0]],"state":"SOLVED","solver":"Daan Rijnkels","verifiers":["John Lewis","Michael Nebesny","Joseph Klopchic"]},{"id":6,"coords":[[0,0,0],[0,0,-1],[0,-1,-1],[0,-2,-1],[-1,0,-1],[1,0,0],[1,1,0],[2,1,0]],"state":"SOLVED","solver":"Keenan Powell","verifiers":["Pranav Ramamurthy","Max Jäger","Brian Schymik"]},{"id":7,"coords":[[0,0,0],[0,0,-1],[0,-1,-1],[0,-1,-2],[-1,0,0],[-1,1,0],[-1,1,1],[1,0,0]],"state":"SOLVED","solver":"Noah Boekweg","verifiers":["Caleb Kavaloff","Viliam Furík","Fernando Gaete"]},{"id":8,"coords":[[0,0,0],[0,0,-1],[0,0,-2],[0,-1,-2],[-1,-1,-2],[0,0,1],[0,1,1],[1,1,1]],"state":"SOLVED","solver":"Steven Schroeder","verifiers":["John Lewis","Nick Hollett","T-Jay_HD"]},{"id":9,"coords":[[0,0,0],[0,0,-1],[0,-1,-1],[0,1,-1],[-1,0,0],[-2,0,0],[1,0,0],[1,0,1]],"state":"SOLVED","solver":"Daan Rijnkels","verifiers":["John Lewis","Asher Margulies","Jack Rickard"]},{"id":10,"coords":[[0,0,0],[0,0,-1],[0,0,-2],[0,-1,-1],[0,0,1],[-1,0,1],[1,0,1],[0,1,0]],"state":"SOLVED","solver":"Pending"},{"id":11,"coords":[[0,0,0],[0,0,-1],[0,-1,-1],[-1,-1,-1],[1,0,0],[2,0,0],[1,0,1],[1,1,0]],"state":"SOLVED","solver":"Ryan Stones","verifiers":["Croma","Saul Roche","Michael Gregory Baska"]},{"id":12,"coords":[[0,0,0],[0,0,-1],[0,0,-2],[0,-1,-2],[-1,0,0],[-1,0,1],[-1,1,0],[1,0,0]],"state":"SOLVED","solver":"Violet Nguyen","verifiers":["Cyprien Heusse","Michael Nebesny","Marcos Petri"]},{"id":13,"coords":[[0,0,0],[0,0,-1],[0,-1,-1],[-1,-1,-1],[1,0,-1],[0,0,1],[0,0,2],[0,1,2]],"state":"SOLVED","solver":"Daan Rijnkels","verifiers":["Chris Dewandeler","John-Luca Feindt","Paulio"]},{"id":14,"coords":[[0,0,0],[0,0,-1],[0,-1,-1],[0,-2,-1],[-1,-1,-1],[1,0,0],[2,0,0],[2,1,0]],"state":"SOLVED","solver":"Pending"},{"id":15,"coords":[[0,0,0],[0,0,-1],[0,0,-2],[0,-1,-2],[-1,0,0],[-1,1,0],[-1,1,1],[1,0,0]],"state":"SOLVED","solver":"Pending"},{"id":16,"coords":[[0,0,0],[0,0,-1],[0,-1,-1],[0,-1,-2],[-1,0,-1],[0,1,0],[1,1,0],[1,1,1]],"state":"SOLVED","solver":"Pending"},{"id":17,"coords":[[0,0,0],[0,0,-1],[0,-1,-1],[0,-1,-2],[-1,0,-1],[1,0,0],[1,1,0],[1,1,1]],"state":"SOLVED","solver":"Pending"},{"id":18,"coords":[[0,0,0],[0,0,-1],[0,-1,-1],[0,-2,-1],[0,1,0],[0,2,0],[-1,1,0],[1,1,0]],"state":"SOLVED","solver":"Pending"},{"id":19,"coords":[[0,0,0],[0,0,-1],[0,-1,-1],[-1,-1,-1],[0,0,1],[0,0,2],[0,1,1],[1,0,0]],"state":"SOLVED","solver":"Pending"},{"id":20,"coords":[[0,0,0],[0,0,-1],[0,-1,-1],[0,-1,-2],[-1,-1,-2],[0,1,0],[0,1,1],[1,1,1]],"state":"SOLVED","solver":"T-Jay Harfleet-Diboll","verifiers":["J.P. Savard","Friday","Lucas Emanuel Genova"]},{"id":21,"coords":[[0,0,0],[0,0,-1],[0,-1,-1],[0,-2,-1],[-1,0,-1],[0,1,0],[1,1,0],[1,2,0]],"state":"SOLVED","solver":"Roy Boggs","verifiers":["Gabriel Leo Denney-Martell","Saul Roche","Viliam Furík"]},{"id":22,"coords":[[0,0,0],[0,0,-1],[0,0,-2],[0,-1,-2],[-1,-1,-2],[1,0,0],[1,0,1],[1,1,1]],"state":"SOLVED","solver":"Zac Apelt","verifiers":["Asher Margulies","T-Jay_HD","Hans Christian Schmitz"]},{"id":23,"coords":[[0,0,0],[0,0,-1],[0,-1,-1],[-1,-1,-1],[0,1,-1],[1,0,0],[2,0,0],[1,0,1]],"state":"SOLVED","solver":"Pending"},{"id":24,"coords":[[0,0,0],[0,0,-1],[0,-1,-1],[0,-1,-2],[-1,-1,-1],[0,0,1],[0,1,1],[1,1,1]],"state":"SOLVED","solver":"Pending"},{"id":25,"coords":[[0,0,0],[0,0,-1],[0,-1,-1],[-1,-1,-1],[0,0,-2],[0,0,1],[1,0,1],[1,1,1]],"state":"SOLVED","solver":"Daan Rijnkels","verifiers":["Dan P","Cyprien Heusse","Chris Dewandeler"]},{"id":26,"coords":[[0,0,0],[0,0,-1],[0,0,-2],[0,-1,-2],[0,1,-1],[0,0,1],[-1,0,1],[1,0,0]],"state":"SOLVED","solver":"Pending"},{"id":27,"coords":[[0,0,0],[0,0,-1],[0,0,-2],[0,0,-3],[0,-1,-2],[-1,0,0],[-1,1,0],[-1,2,0]],"state":"SOLVED","solver":"Julian Ahl","verifiers":["Robbe Pincket","Jonas Schöne","Yuval Talya Nehemia"]},{"id":28,"coords":[[0,0,0],[0,0,-1],[0,0,-2],[0,-1,-2],[0,1,0],[0,1,1],[-1,1,0],[1,0,0]],"state":"SOLVED","solver":"Gerben Beintema","verifiers":["Balázs Makrai-Kis","Luis Fernando Lara Madrid","Devin Danko"]},{"id":29,"coords":[[0,0,0],[0,0,-1],[0,-1,-1],[-1,0,-1],[0,0,1],[0,0,2],[0,1,0],[1,0,0]],"state":"SOLVED","solver":"Pending"},{"id":30,"coords":[[0,0,0],[0,0,-1],[0,0,-2],[0,-1,-2],[-1,0,0],[-1,0,1],[0,1,0],[1,1,0]],"state":"SOLVED","solver":"Spencer Myers","verifiers":["Jack Ellert-Beck","William Forrest Drayer","evan.breznyik@gmail.com"]},{"id":31,"coords":[[0,0,0],[0,0,-1],[0,-1,-1],[0,-2,-1],[0,1,-1],[-1,0,0],[-2,0,0],[1,0,0]],"state":"SOLVED","solver":"T-Jay Harfleet-Diboll","verifiers":["Andrea Consonni","Javier","Charlie Brady"]},{"id":32,"coords":[[0,0,0],[0,0,-1],[0,-1,-1],[0,-1,-2],[-1,0,0],[-1,1,0],[0,0,1],[1,0,0]],"state":"SOLVED","solver":"Henry Coyle","verifiers":["Matthew Murphy","Lucas Albers","Koen Timmermans"]},{"id":33,"coords":[[0,0,0],[0,0,-1],[0,-1,-1],[-1,0,-1],[0,0,1],[0,0,2],[0,1,0],[1,1,0]],"state":"SOLVED","solver":"Jonathan Ralphs","verifiers":["Jonathan Burgess","Daniel Diggs","Mikuláš Fiala"]},{"id":34,"coords":[[0,0,0],[0,0,-1],[0,-1,-1],[-1,-1,-1],[0,1,0],[0,2,0],[0,0,1],[1,0,1]],"state":"SOLVED","solver":"Daniel Grenier","verifiers":["Luis Novoa","MooseMoss","Tillmann Sliwinski"]},{"id":35,"coords":[[0,0,0],[0,0,-1],[0,0,-2],[0,-1,-2],[-1,0,-1],[0,1,0],[0,1,1],[1,1,1]],"state":"SOLVED","solver":"Pending"},{"id":36,"coords":[[0,0,0],[0,0,-1],[0,0,-2],[0,-1,-2],[0,-1,-3],[-1,0,0],[-1,1,0],[-1,2,0]],"state":"SOLVED","solver":"Alex Renton","verifiers":["Fernando Gaete","david@jellybaby.net","Jacob Molea"]},{"id":37,"coords":[[0,0,0],[0,0,-1],[0,-1,-1],[0,-1,-2],[0,0,1],[-1,0,1],[1,0,1],[0,1,0]],"state":"SOLVED","solver":"Liam Appelbe","verifiers":["Stephen Brown","Viliam Furík","John-Luca Feindt"]},{"id":38,"coords":[[0,0,0],[0,0,-1],[0,-1,-1],[0,-2,-1],[0,1,0],[0,2,0],[-1,1,0],[1,0,0]],"state":"SOLVED","solver":"Roy Boggs","verifiers":["Michael Gorbunov","Eric Bardroff","Paddy Kenworthy"]},{"id":39,"coords":[[0,0,0],[0,0,-1],[0,-1,-1],[0,1,-1],[0,0,1],[0,0,2],[-1,0,0],[1,0,0]],"state":"SOLVED","solver":"Linus Erlenbusch","verifiers":["Kyle Doney","Mikuláš Fiala","Marcin Makowski"]},{"id":40,"coords":[[0,0,0],[0,0,-1],[0,-1,-1],[0,-1,-2],[-1,0,0],[-1,0,1],[1,0,0],[1,1,0]],"state":"SOLVED","solver":"Dean Hortin","verifiers":["Kirill Zolotuskiy","Neil Sullivan","r10pez10"]},{"id":41,"coords":[[0,0,0],[0,0,-1],[0,0,-2],[0,-1,-2],[-1,0,0],[-1,0,1],[0,1,0],[1,0,0]],"state":"SOLVED","solver":"Sven Neumann","verifiers":["André Løfaldli","Asher Margulies","Jonathan Süße"]},{"id":42,"coords":[[0,0,0],[0,0,-1],[0,0,-2],[0,-1,-2],[-1,0,-1],[1,0,0],[1,1,0],[0,0,1]],"state":"SOLVED","solver":"Alex Renton","verifiers":["Kevin Gomez","Lopoi","Louis Davies"]},{"id":43,"coords":[[0,0,0],[0,0,-1],[0,-1,-1],[0,-2,-1],[-1,-1,-1],[0,1,0],[0,2,0],[1,2,0]],"state":"SOLVED","solver":"Filipe Delduque da Costa","verifiers":["Felipe Jannarone","Rick Rijpers","Robbie Tavener"]},{"id":44,"coords":[[0,0,0],[0,0,-1],[0,0,-2],[0,-1,-1],[-1,0,-1],[0,1,0],[0,1,1],[1,1,0]],"state":"SOLVED","solver":"Liam Appelbe","verifiers":["Christian Semrau","Lea Rajala","Frankie Mercado"]},{"id":45,"coords":[[0,0,0],[0,0,-1],[0,0,-2],[0,-1,-1],[0,1,0],[0,1,1],[-1,1,0],[1,0,0]],"state":"SOLVED","solver":"Jack Rickard","verifiers":["John-Luca Feindt","Ryan Weisenburger","Tillmann Sliwinski"]},{"id":46,"coords":[[0,0,0],[0,0,-1],[0,0,-2],[0,-1,0],[0,-1,1],[0,1,0],[-1,1,0],[1,0,0]],"state":"SOLVED","solver":"Zac Apelt","verifiers":["Justin Maddux","Jonas Schöne","Joseph"]},{"id":47,"coords":[[0,0,0],[0,0,-1],[0,-1,-1],[0,1,-1],[-1,0,-1],[1,0,0],[2,0,0],[0,0,1]],"state":"SOLVED","solver":"Matt Merrill","verifiers":["Daan Rijnkels","Kieran Hingston","GwynBleidD"]},{"id":48,"coords":[[0,0,0],[0,0,-1],[0,-1,-1],[0,-1,-2],[-1,0,-1],[1,0,0],[1,1,0],[0,0,1]],"state":"SOLVED","solver":"George Staniforth","verifiers":["Hagen von Eitzen","James McClure","David Blättler"]},{"id":49,"coords":[[0,0,0],[0,0,-1],[0,0,-2],[0,-1,-2],[-1,0,-1],[0,0,1],[0,1,1],[1,0,1]],"state":"SOLVED","solver":"Walter Luers","verifiers":["Pranav Ramamurthy","Tyler Reynolds","Joseph Marrow"]},{"id":50,"coords":[[0,0,0],[0,0,-1],[0,-1,-1],[-1,-1,-1],[0,1,0],[0,2,0],[0,1,1],[1,0,0]],"state":"SOLVED","solver":"Pending"},{"id":51,"coords":[[0,0,0],[0,0,-1],[0,-1,-1],[-1,-1,-1],[0,0,-2],[1,0,0],[1,0,1],[1,1,1]],"state":"SOLVED","solver":"Matan (Matt) Kazachinsky","verifiers":["Matthew Gerry","John Pearce","Arnout Huysmans"]},{"id":52,"coords":[[0,0,0],[0,0,-1],[0,-1,-1],[0,1,-1],[-1,0,-1],[1,0,0],[2,0,0],[1,0,1]],"state":"SOLVED","solver":"Bálint Csanády and Alicja Janiszewska","verifiers":["Gage Schacher","Charles-Émile Fecteau","valentin comte"]},{"id":53,"coords":[[0,0,0],[0,0,-1],[0,-1,-1],[0,-1,-2],[-1,0,-1],[0,1,0],[1,1,0],[0,0,1]],"state":"SOLVED","solver":"Pending"},{"id":54,"coords":[[0,0,0],[0,0,-1],[0,-1,-1],[-1,-1,-1],[0,0,-2],[1,0,0],[1,1,0],[0,0,1]],"state":"SOLVED","solver":"Chase Garrett","verifiers":["Eddie Heyne","Valerio Brogni","Daniel Herrera"]},{"id":55,"coords":[[0,0,0],[0,0,-1],[0,-1,-1],[0,-1,-2],[0,1,0],[0,1,1],[-1,1,1],[1,0,0]],"state":"SOLVED","solver":"Mauricio Bolivar","verifiers":["Robbe Pincket","Fernando Gaete","Pranav Ramamurthy"]},{"id":56,"coords":[[0,0,0],[0,0,-1],[0,0,-2],[0,0,-3],[0,-1,-2],[0,1,0],[-1,1,0],[1,1,0]],"state":"SOLVED","solver":"Jordyn Hyde","verifiers":["Daan Rijnkels","Nathan M Gilbert","Max Jäger"]},{"id":57,"coords":[[0,0,0],[0,0,-1],[0,0,-2],[0,-1,-1],[0,1,-1],[-1,0,-1],[1,0,0],[1,0,1]],"state":"SOLVED","solver":"Pending"},{"id":58,"coords":[[0,0,0],[0,0,-1],[0,0,-2],[0,-1,-2],[0,1,0],[0,1,1],[-1,0,0],[1,0,0]],"state":"SOLVED","solver":"Camden K","verifiers":["Michael B Murray","Javier","Anhadvir Singh"]},{"id":59,"coords":[[0,0,0],[0,0,-1],[0,-1,-1],[0,-2,-1],[0,0,-2],[-1,0,0],[-1,1,0],[1,0,0]],"state":"SOLVED","solver":"Anhadvir Singh","verifiers":["Jason Wang","Reed Pratt","Zakir"]},{"id":60,"coords":[[0,0,0],[0,0,-1],[0,-1,-1],[-1,-1,-1],[0,0,-2],[0,1,0],[0,1,1],[1,1,1]],"state":"SOLVED","solver":"Liam Appelbe","verifiers":["Dmitriy Molostvov","Oscar Oweson","Xavier Lamphere"]},{"id":61,"coords":[[0,0,0],[0,0,-1],[0,-1,-1],[0,-1,-2],[-1,0,-1],[1,0,0],[1,0,1],[1,1,0]],"state":"SOLVED","solver":"Jesse Vermeire","verifiers":["Joseph W","Pieter van Zoelen","dadalev"]},{"id":62,"coords":[[0,0,0],[0,0,-1],[0,0,-2],[0,0,-3],[0,-1,0],[-1,-1,0],[1,-1,0],[0,1,0]],"state":"SOLVED","solver":"Jordyn Hyde","verifiers":["T-Jay_HD","Mitchell Avallone","m.ali.a"]},{"id":63,"coords":[[0,0,0],[0,0,-1],[0,-1,-1],[-1,-1,-1],[1,0,-1],[0,1,0],[0,2,0],[0,2,1]],"state":"SOLVED","solver":"Pieter van Zoelen","verifiers":["Vito Kekin","Asher","Måns Andersen"]},{"id":64,"coords":[[0,0,0],[0,0,-1],[0,0,-2],[0,-1,-2],[-1,0,-1],[1,0,0],[1,0,1],[1,1,1]],"state":"SOLVED","solver":"Michael B Murray","verifiers":["Felipe Jannarone","Caleb Kavaloff","Roman Berens"]},{"id":65,"coords":[[0,0,0],[0,0,-1],[0,0,-2],[0,0,1],[0,-1,1],[0,1,0],[-1,0,0],[1,0,0]],"state":"SOLVED","solver":"Pending"},{"id":66,"coords":[[0,0,0],[0,0,-1],[0,-1,-1],[0,1,-1],[-1,0,-1],[0,0,1],[0,0,2],[1,0,0]],"state":"SOLVED","solver":"Andre Leue","verifiers":["Luke Rennells","Vietbao Tran","Gustavo Tontini"]},{"id":67,"coords":[[0,0,0],[0,0,-1],[0,-1,-1],[-1,-1,-1],[0,0,1],[0,0,2],[0,1,0],[1,1,0]],"state":"SOLVED","solver":"Pending"},{"id":68,"coords":[[0,0,0],[0,0,-1],[0,-1,-1],[0,-2,-1],[0,1,0],[0,2,0],[-1,0,0],[1,0,0]],"state":"SOLVED","solver":"anonymous","verifiers":["Robbe Pincket","Jordyn Hyde","Pavel Rozhkov"]},{"id":69,"coords":[[0,0,0],[0,0,-1],[0,0,-2],[0,-1,-1],[0,0,1],[0,1,0],[-1,0,0],[1,0,0]],"state":"SOLVED","solver":"Anders Martin Kval","verifiers":["J.P. Savard","Filipe Delduque da Costa","Anhadvir Singh"]},{"id":70,"coords":[[0,0,0],[0,0,-1],[0,0,-2],[0,-1,-2],[-1,0,-1],[1,0,0],[1,0,1],[1,1,0]],"state":"SOLVED","solver":"Max Hofman","verifiers":["Simon E.M.","Jason Wang","Lucas Emanuel Genova"]},{"id":71,"coords":[[0,0,0],[0,0,-1],[0,-1,-1],[-1,-1,-1],[0,0,-2],[0,0,1],[0,1,1],[1,1,1]],"state":"SOLVED","solver":"Jordyn Hyde","verifiers":["Philip Peal","Klavs Riekstins ","Jarrod Scherer"]},{"id":72,"coords":[[0,0,0],[0,0,-1],[0,-1,-1],[0,-2,-1],[0,1,-1],[-1,0,0],[-2,0,0],[-3,0,0]],"state":"SOLVED","solver":"Jose Antonio Gonzalez","verifiers":["Daan Rijnkels","Jordyn Hyde","Bryan Lee Williams"]},{"id":73,"coords":[[0,0,0],[0,0,-1],[0,-1,-1],[0,-2,-1],[-1,-2,-1],[0,1,0],[0,2,0],[1,2,0]],"state":"SOLVED","solver":"Matt Parker","verifiers":["Stuart Ward","Octavia Togami","Andrea Consonni"]},{"id":74,"coords":[[0,0,0],[0,0,-1],[0,0,-2],[0,-1,-1],[0,1,-1],[0,0,1],[-1,0,0],[1,0,0]],"state":"SOLVED","solver":"Giovanna Diaz and Joseph O'Rourke","verifiers":[]},{"id":75,"coords":[[0,0,0],[0,0,-1],[0,-1,-1],[0,-1,-2],[0,0,1],[0,1,1],[-1,0,1],[1,0,0]],"state":"SOLVED","solver":"Tim Rexrodt","verifiers":["Julian Ahl","José Sousa","Petr Dymanus"]},{"id":76,"coords":[[0,0,0],[0,0,-1],[0,0,-2],[0,-1,-1],[-1,0,0],[-1,1,0],[0,0,1],[1,0,0]],"state":"SOLVED","solver":"Marcos Vinicius Petri","verifiers":["Elise Baczek","Ruaraidh Middleton","Jamie Rogers"]},{"id":77,"coords":[[0,0,0],[0,0,-1],[0,-1,-1],[-1,-1,-1],[1,0,0],[2,0,0],[0,0,1],[0,1,0]],"state":"SOLVED","solver":"Max Hofman","verifiers":["Garrison Burger","Ben Sanby","Caleb Kavaloff"]},{"id":78,"coords":[[0,0,0],[0,0,-1],[0,-1,-1],[0,-1,-2],[-1,-1,-1],[1,0,0],[1,0,1],[1,1,1]],"state":"SOLVED","solver":"Pending"},{"id":79,"coords":[[0,0,0],[0,0,-1],[0,-1,-1],[0,-1,-2],[0,1,0],[0,1,1],[-1,1,0],[1,0,0]],"state":"SOLVED","solver":"Moritz Ernst Jacob","verifiers":["Jacobo","Åsmund Aqissiaq Arild Kløvstad","Itay Czaczkes"]},{"id":80,"coords":[[0,0,0],[0,0,-1],[0,-1,-1],[-1,-1,-1],[0,1,-1],[0,0,1],[0,0,2],[1,0,2]],"state":"SOLVED","solver":"jonas malice","verifiers":["Louis Davies","Croma","Anton Christensen"]},{"id":81,"coords":[[0,0,0],[0,0,-1],[0,0,-2],[0,-1,-1],[0,1,-1],[-1,0,-1],[0,0,1],[1,0,1]],"state":"SOLVED","solver":"Pending"},{"id":82,"coords":[[0,0,0],[0,0,-1],[0,-1,-1],[0,-1,-2],[-1,0,0],[-1,0,1],[-1,0,2],[0,1,0]],"state":"SOLVED","solver":"Jason DiMase","verifiers":["zoey pridan","John Armstrong","Oliver Hood"]},{"id":83,"coords":[[0,0,0],[0,0,-1],[0,0,-2],[0,-1,0],[-1,-1,0],[0,1,0],[1,1,0],[0,0,1]],"state":"SOLVED","solver":"Jordyn Hyde","verifiers":["John Pearce","Sullivan Figurskey","Pranav Ramamurthy"]},{"id":84,"coords":[[0,0,0],[0,0,-1],[0,0,-2],[0,-1,-1],[-1,0,-1],[0,0,1],[0,1,1],[1,0,1]],"state":"SOLVED","solver":"Terry Honk","verifiers":["Charles-Émile Fecteau","Tomáš Mráka","Noah Jerry Boekweg"]},{"id":85,"coords":[[0,0,0],[0,0,-1],[0,-1,-1],[-1,-1,-1],[0,1,0],[0,2,0],[0,1,1],[1,1,0]],"state":"SOLVED","solver":"Pending"},{"id":86,"coords":[[0,0,0],[0,0,-1],[0,-1,-1],[0,-1,-2],[0,1,0],[0,1,1],[-1,1,0],[1,1,0]],"state":"SOLVED","solver":"Niels Norberg","verifiers":["Gabriel Leo Denney-Martell","Roy Boggs","Kenneth Harold Johnson"]},{"id":87,"coords":[[0,0,0],[0,0,-1],[0,-1,-1],[-1,-1,-1],[0,0,-2],[0,0,1],[0,1,1],[1,0,1]],"state":"SOLVED","solver":"Kaelygon","verifiers":["John Lewis","Henry Coyle","Balázs Makrai-Kis"]},{"id":88,"coords":[[0,0,0],[0,0,-1],[0,-1,-1],[0,-1,-2],[-1,0,-1],[0,1,0],[0,1,1],[1,1,1]],"state":"SOLVED","solver":"Bálint Csanády","verifiers":["Lucas Damasceno","Tomáš Mráka","William Knowles-Kellett"]},{"id":89,"coords":[[0,0,0],[0,0,-1],[0,-1,-1],[0,-1,-2],[-1,0,0],[-1,0,1],[0,1,0],[1,0,0]],"state":"SOLVED","solver":"Malachi Voss","verifiers":["Neil Sullivan","Konrad Pitt","T-Jay_HD"]},{"id":90,"coords":[[0,0,0],[0,0,-1],[0,0,-2],[0,-1,-2],[0,1,0],[0,1,1],[-1,1,1],[1,0,0]],"state":"SOLVED","solver":"Theo Hiraclides","verifiers":["Dari A-F","Edward Green","John-Luca Feindt"]},{"id":91,"coords":[[0,0,0],[0,0,-1],[0,0,-2],[0,-1,-2],[0,0,1],[-1,0,1],[-1,1,1],[1,0,0]],"state":"SOLVED","solver":"Tillmann Sliwinski","verifiers":["Kenan","Jonathan Süße","Marcin Makowski"]},{"id":92,"coords":[[0,0,0],[0,0,-1],[0,-1,-1],[0,-2,-1],[-1,-1,-1],[0,1,0],[0,2,0],[1,1,0]],"state":"SOLVED","solver":"Lode Vandevenne","verifiers":["Daan Rijnkels","Jordyn Hyde","Benjamin Swart"]},{"id":93,"coords":[[0,0,0],[0,0,-1],[0,0,-2],[0,-1,-2],[-1,-1,-2],[1,0,0],[1,1,0],[1,1,1]],"state":"SOLVED","solver":"Valerio Brogni","verifiers":["Rafael Bailo","Jason Wang","T-Jay_HD"]},{"id":94,"coords":[[0,0,0],[0,0,-1],[0,-1,-1],[0,-2,-1],[0,-2,-2],[-1,0,0],[-1,1,0],[-1,2,0]],"state":"SOLVED","solver":"Jason DiMase","verifiers":["Lucas Albers","Sullivan Figurskey","Eric Bardroff"]},{"id":95,"coords":[[0,0,0],[0,0,-1],[0,-1,-1],[0,-2,-1],[-1,0,-1],[1,0,0],[2,0,0],[1,1,0]],"state":"SOLVED","solver":"Shannon Ryan","verifiers":["Yuval Talya Nehemia","Jeppe Jon Holt","Zakir"]},{"id":96,"coords":[[0,0,0],[0,0,-1],[0,0,-2],[0,-1,-1],[-1,0,-1],[0,1,0],[0,1,1],[1,0,0]],"state":"SOLVED","solver":"Jort Gutter","verifiers":["jonas malice","Charlie Brady","Zakir"]},{"id":97,"coords":[[0,0,0],[0,0,-1],[0,0,-2],[0,-1,-2],[0,1,-2],[0,0,1],[-1,0,1],[1,0,1]],"state":"SOLVED","solver":"Ethan Buttimer","verifiers":["Viliam Furík","Oliver Hood","Kenneth Harold Johnson"]},{"id":98,"coords":[[0,0,0],[0,0,-1],[0,-1,-1],[0,-1,-2],[0,-2,-2],[-1,0,0],[-1,1,0],[-1,2,0]],"state":"SOLVED","solver":"Jose Antonio Gonzalez","verifiers":["Daan Rijnkels","r10pez10","Nick Hollett"]},{"id":99,"coords":[[0,0,0],[0,0,-1],[0,0,-2],[0,-1,-1],[0,1,0],[-1,1,0],[1,1,0],[0,0,1]],"state":"SOLVED","solver":"Jordyn Hyde","verifiers":["Andre Leue","Marcos Petri","Ellie Vallard"]},{"id":100,"coords":[[0,0,0],[0,0,-1],[0,-1,-1],[-1,0,-1],[0,1,0],[0,2,0],[1,0,0],[1,0,1]],"state":"SOLVED","solver":"Jackson Kilger","verifiers":["Sean Wheeldon","Mariusz","Vytis Banaitis"]},{"id":101,"coords":[[0,0,0],[0,0,-1],[0,-1,-1],[-1,-1,-1],[0,1,-1],[0,0,1],[1,0,1],[1,0,2]],"state":"SOLVED","solver":"David Rollo","verifiers":["Pieter van Zoelen","John Lewis","Dari A-F"]},{"id":102,"coords":[[0,0,0],[0,0,-1],[0,-1,-1],[0,1,-1],[-1,0,-1],[1,0,-1],[0,0,1],[0,0,2]],"state":"SOLVED","solver":"Ivan Hadevych","verifiers":["Viliam Furík","zoey pridan","Carson Jones"]},{"id":103,"coords":[[0,0,0],[0,0,-1],[0,0,-2],[0,-1,-2],[0,0,1],[0,1,1],[-1,0,0],[1,0,0]],"state":"SOLVED","solver":"Alexandru Constantin Corduban","verifiers":["Simon Green \"Duckapple\" Kristensen","Kenan","Charles-Émile Fecteau"]},{"id":104,"coords":[[0,0,0],[0,0,-1],[0,-1,-1],[-1,-1,-1],[1,-1,-1],[0,1,0],[0,2,0],[0,2,1]],"state":"SOLVED","solver":"Andrea Lisa","verifiers":["Jacobo","Roy Boggs","William Fisher"]},{"id":105,"coords":[[0,0,0],[0,0,-1],[0,0,-2],[0,-1,-2],[-1,0,-2],[0,0,1],[0,1,1],[1,0,1]],"state":"SOLVED","solver":"John Armstrong","verifiers":["Shane Gleeson","Glenn Jenkins","Gabriel Loureiro Faria Vasconcelos"]},{"id":106,"coords":[[0,0,0],[0,0,-1],[0,0,-2],[0,0,1],[0,-1,1],[0,1,0],[-1,1,0],[1,0,0]],"state":"SOLVED","solver":"Aleš Chudárek","verifiers":["Garrick Glickenhouse","Eric Rodriguez","David Fichtmueller"]},{"id":107,"coords":[[0,0,0],[0,0,-1],[0,0,-2],[0,-1,-2],[0,0,1],[-1,0,1],[0,1,0],[1,1,0]],"state":"SOLVED","solver":"Pending"},{"id":108,"coords":[[0,0,0],[0,0,-1],[0,-1,-1],[0,-1,-2],[-1,0,-1],[0,0,1],[0,1,1],[1,1,1]],"state":"SOLVED","solver":"Pending"},{"id":109,"coords":[[0,0,0],[0,0,-1],[0,-1,-1],[0,-1,-2],[0,1,0],[-1,1,0],[-1,1,1],[1,0,0]],"state":"SOLVED","solver":"Lewis Sugden","verifiers":["Gabriel Leo Denney-Martell","zoey pridan","Jack Ellert-Beck"]},{"id":110,"coords":[[0,0,0],[0,0,-1],[0,-1,-1],[0,-1,-2],[0,-2,-1],[0,1,0],[-1,1,0],[1,1,0]],"state":"SOLVED","solver":"Liam Appelbe","verifiers":["Jordyn Hyde","Nathan George","Jamie Papworth-Dent"]},{"id":111,"coords":[[0,0,0],[0,0,-1],[0,0,-2],[0,-1,-2],[-1,0,-2],[0,1,0],[0,1,1],[1,1,1]],"state":"SOLVED","solver":"Hee Wah Jun","verifiers":["Eric Clayton","Jakob Schultz","Émile Sterner Jonsson"]},{"id":112,"coords":[[0,0,0],[0,0,-1],[0,-1,-1],[0,-1,-2],[0,0,1],[-1,0,1],[0,1,0],[1,0,0]],"state":"SOLVED","solver":"Apollo Albright","verifiers":["Jonathan Burgess","Tommy Räjert","Dmitriy Molostvov"]},{"id":113,"coords":[[0,0,0],[0,0,-1],[0,-1,-1],[-1,-1,-1],[1,0,-1],[0,1,0],[0,1,1],[0,2,1]],"state":"SOLVED","solver":"Jason Gray","verifiers":["Chris Ballard","Balázs Makrai-Kis","Daan Rijnkels"]},{"id":114,"coords":[[0,0,0],[0,0,-1],[0,-1,-1],[0,1,-1],[-1,0,0],[-2,0,0],[0,0,1],[1,0,1]],"state":"SOLVED","solver":"Demtien","verifiers":["EbbDrop","Felipe Jannarone","Cyprien Heusse"]},{"id":115,"coords":[[0,0,0],[0,0,-1],[0,0,-2],[0,-1,0],[0,-1,1],[-1,0,0],[-1,1,0],[1,0,0]],"state":"SOLVED","solver":"Cookie Cherith","verifiers":["Thomas Fugikawa","David J. Webb","Lucas Emanuel Genova"]},{"id":116,"coords":[[0,0,0],[0,0,-1],[0,0,-2],[0,0,-3],[0,-1,-3],[-1,0,0],[-1,1,0],[-1,2,0]],"state":"SOLVED","solver":"Milan Durnell","verifiers":["kipff","Daan Rijnkels","Glenn Jenkins"]},{"id":117,"coords":[[0,0,0],[0,0,-1],[0,-1,-1],[-1,-1,-1],[0,0,-2],[0,1,0],[1,1,0],[0,0,1]],"state":"SOLVED","solver":"Pending"},{"id":118,"coords":[[0,0,0],[0,0,-1],[0,-1,-1],[-1,-1,-1],[1,0,-1],[0,0,1],[0,0,2],[0,1,1]],"state":"SOLVED","solver":"Henrique Colini","verifiers":["Robbe Pincket","Keith Sullivan","Andre Leue"]},{"id":119,"coords":[[0,0,0],[0,0,-1],[0,0,-2],[0,-1,-1],[0,1,0],[0,1,1],[-1,0,0],[1,0,0]],"state":"SOLVED","solver":"Diandras Šližys","verifiers":["Jeppe Jon Holt","Esaias Tilly","Jonathan Süße"]},{"id":120,"coords":[[0,0,0],[0,0,-1],[0,-1,-1],[0,-2,-1],[0,-3,-1],[-1,0,0],[-2,0,0],[-3,0,0]],"state":"SOLVED","solver":"Steven Stadnicki","verifiers":[]},{"id":121,"coords":[[0,0,0],[0,0,-1],[0,0,-2],[0,0,-3],[0,-1,0],[-1,-1,0],[1,0,0],[1,1,0]],"state":"SOLVED","solver":"Rachael Silverwood","verifiers":["Daan Rijnkels","Nathan M Gilbert","Max Jäger"]},{"id":122,"coords":[[0,0,0],[0,0,-1],[0,-1,-1],[0,-1,-2],[-1,-1,-2],[1,0,0],[1,1,0],[1,1,1]],"state":"SOLVED","solver":"Pavel Rozhkov","verifiers":["Pieter van Zoelen","Daniel Herrera","Metin Suloglu"]},{"id":123,"coords":[[0,0,0],[0,0,-1],[0,0,-2],[0,-1,-2],[0,0,1],[0,1,1],[-1,1,1],[1,0,0]],"state":"SOLVED","solver":"Niall Arthurs","verifiers":["Donovan Kuo","Marco","Daan Rijnkels"]},{"id":124,"coords":[[0,0,0],[0,0,-1],[0,0,-2],[0,-1,-1],[0,1,-1],[0,0,1],[-1,0,1],[1,0,0]],"state":"SOLVED","solver":"Petros Mavromichalis","verifiers":["Dari A-F","Damien Wells","Ben Hellinga"]},{"id":125,"coords":[[0,0,0],[0,0,-1],[0,-1,-1],[0,-1,-2],[0,0,1],[-1,0,1],[0,1,0],[1,1,0]],"state":"SOLVED","solver":"Pending"},{"id":126,"coords":[[0,0,0],[0,0,-1],[0,0,-2],[0,-1,-2],[-1,0,-1],[0,1,0],[1,1,0],[0,0,1]],"state":"SOLVED","solver":"Pending"},{"id":127,"coords":[[0,0,0],[0,0,-1],[0,-1,-1],[-1,-1,-1],[1,0,0],[2,0,0],[1,1,0],[0,0,1]],"state":"SOLVED","solver":"Eric Lappalainen","verifiers":["TNT Dragon","Viliam Furík","Louis Davies"]},{"id":128,"coords":[[0,0,0],[0,0,-1],[0,-1,-1],[0,-1,-2],[0,-2,-1],[-1,0,0],[-1,1,0],[-1,2,0]],"state":"SOLVED","solver":"Pending"},{"id":129,"coords":[[0,0,0],[0,0,-1],[0,0,-2],[0,-1,-1],[0,1,-1],[-1,0,0],[-1,0,1],[1,0,0]],"state":"SOLVED","solver":"Pending"},{"id":130,"coords":[[0,0,0],[0,0,-1],[0,-1,-1],[-1,-1,-1],[0,1,-1],[1,0,0],[1,0,1],[2,0,1]],"state":"SOLVED","solver":"Pending"},{"id":131,"coords":[[0,0,0],[0,0,-1],[0,0,-2],[0,-1,-2],[-1,0,-1],[0,1,0],[0,1,1],[1,0,0]],"state":"SOLVED","solver":"Pending"},{"id":132,"coords":[[0,0,0],[0,0,-1],[0,0,-2],[0,-1,-2],[0,1,-1],[-1,0,0],[-1,0,1],[1,0,0]],"state":"SOLVED","solver":"Pending"},{"id":133,"coords":[[0,0,0],[0,0,-1],[0,-1,-1],[0,-1,-2],[-1,0,-1],[0,0,1],[0,1,1],[1,0,1]],"state":"SOLVED","solver":"Philip Dale","verifiers":["Jack Lloyd-Walters","John-Luca Feindt","Oliver Hood"]},{"id":134,"coords":[[0,0,0],[0,0,-1],[0,-1,-1],[0,-1,-2],[0,1,0],[-1,1,0],[1,1,0],[0,0,1]],"state":"SOLVED","solver":"Pending"},{"id":135,"coords":[[0,0,0],[0,0,-1],[0,0,-2],[0,-1,-1],[0,1,-1],[0,0,1],[-1,0,1],[1,0,1]],"state":"SOLVED","solver":"Hjalmar Rusck","verifiers":["Simon E.M.","Jonathan Burgess","Levente Hartstang"]},{"id":136,"coords":[[0,0,0],[0,0,-1],[0,-1,-1],[0,-1,-2],[-1,-1,-1],[0,1,0],[0,1,1],[1,1,1]],"state":"SOLVED","solver":"Pending"},{"id":137,"coords":[[0,0,0],[0,0,-1],[0,-1,-1],[0,-1,-2],[0,0,1],[0,1,1],[-1,1,1],[1,0,0]],"state":"SOLVED","solver":"Benjamin Grant","verifiers":["Stephen Brown","zoey pridan","Eddie Heyne"]},{"id":138,"coords":[[0,0,0],[0,0,-1],[0,0,-2],[0,-1,-2],[-1,-1,-2],[0,1,0],[0,1,1],[1,1,1]],"state":"SOLVED","solver":"Pending"},{"id":139,"coords":[[0,0,0],[0,0,-1],[0,-1,-1],[0,-1,-2],[0,-1,-3],[-1,0,0],[-1,0,1],[-1,0,2]],"state":"SOLVED","solver":"Steven Stadnicki","verifiers":[]},{"id":140,"coords":[[0,0,0],[0,0,-1],[0,-1,-1],[-1,-1,-1],[-1,-2,-1],[0,1,0],[0,2,0],[1,2,0]],"state":"SOLVED","solver":"Andrew Taylor","verifiers":["Oke Petersen","m.ali.a","Dmitriy Molostvov"]},{"id":141,"coords":[[0,0,0],[0,0,-1],[0,-1,-1],[0,-2,-1],[-1,-1,-1],[1,0,0],[1,1,0],[2,1,0]],"state":"SOLVED","solver":"Eduard Volf","verifiers":["Eric Rodriguez","Randy Cox","Reed Pratt"]},{"id":142,"coords":[[0,0,0],[0,0,-1],[0,-1,-1],[0,-2,-1],[-1,0,-1],[1,0,0],[2,0,0],[2,1,0]],"state":"SOLVED","solver":"Sébastien Chagnon","verifiers":["Alban VACHETTE","Marcos Petri","Brady Hasse"]},{"id":143,"coords":[[0,0,0],[0,0,-1],[0,-1,-1],[-1,-1,-1],[1,-1,-1],[0,0,1],[0,1,1],[0,1,2]],"state":"SOLVED","solver":"Emma Wolthuis","verifiers":["Denis Ott","Peter Gagliardi","Croma"]},{"id":144,"coords":[[0,0,0],[0,0,-1],[0,0,-2],[0,0,-3],[0,-1,-1],[0,1,0],[-1,1,0],[1,1,0]],"state":"SOLVED","solver":"Jordyn Hyde","verifiers":["Daan Rijnkels","John Lewis","Ashley Cusack"]},{"id":145,"coords":[[0,0,0],[0,0,-1],[0,-1,-1],[0,-2,-1],[-1,0,-1],[0,1,0],[0,2,0],[1,0,0]],"state":"SOLVED","solver":"Pending"},{"id":146,"coords":[[0,0,0],[0,0,-1],[0,-1,-1],[-1,-1,-1],[0,0,1],[0,0,2],[0,1,0],[1,0,0]],"state":"SOLVED","solver":"Simon Husby","verifiers":["LostLi","Melamine","Aaron Prince"]},{"id":147,"coords":[[0,0,0],[0,0,-1],[0,0,-2],[0,-1,-2],[-1,0,-1],[0,0,1],[1,0,1],[0,1,0]],"state":"SOLVED","solver":"Eduard Volf","verifiers":["Felipe Jannarone","Devin Danko","Vito Kekin"]},{"id":148,"coords":[[0,0,0],[0,0,-1],[0,0,-2],[0,-1,-1],[-1,0,0],[-1,0,1],[0,1,0],[1,1,0]],"state":"SOLVED","solver":"Pending"},{"id":149,"coords":[[0,0,0],[0,0,-1],[0,-1,-1],[0,-1,-2],[-1,0,-1],[1,0,0],[1,0,1],[0,1,0]],"state":"SOLVED","solver":"Jesse Vermeire","verifiers":["Johannes Ebner","Todd Spillers Jr","Máté Pszota"]},{"id":150,"coords":[[0,0,0],[0,0,-1],[0,-1,-1],[0,-1,-2],[0,0,1],[-1,0,1],[1,0,0],[1,1,0]],"state":"SOLVED","solver":"Pending"},{"id":151,"coords":[[0,0,0],[0,0,-1],[0,-1,-1],[-1,-1,-1],[1,0,-1],[0,0,1],[0,1,1],[0,1,2]],"state":"SOLVED","solver":"Pending"},{"id":152,"coords":[[0,0,0],[0,0,-1],[0,0,-2],[0,-1,-2],[-1,0,-1],[0,0,1],[0,1,1],[1,0,0]],"state":"SOLVED","solver":"Itamar Levy","verifiers":["Oke Petersen","John Lewis","Sven Neumann"]},{"id":153,"coords":[[0,0,0],[0,0,-1],[0,-1,-1],[-1,-1,-1],[0,1,-1],[0,0,1],[0,0,2],[1,0,1]],"state":"SOLVED","solver":"Nicholas Pickett","verifiers":["Esran Douma","Lucas Emanuel Genova","Lotte Neubüser"]},{"id":154,"coords":[[0,0,0],[0,0,-1],[0,-1,-1],[-1,-1,-1],[0,1,-1],[1,0,0],[2,0,0],[2,0,1]],"state":"SOLVED","solver":"Einar Eide","verifiers":["Balázs Makrai-Kis","Courtney Pettersen","Mees Broer"]},{"id":155,"coords":[[0,0,0],[0,0,-1],[0,0,-2],[0,-1,0],[0,-1,1],[0,1,0],[-1,0,0],[1,0,0]],"state":"SOLVED","solver":"Pending"},{"id":156,"coords":[[0,0,0],[0,0,-1],[0,0,-2],[0,-1,-2],[0,1,0],[-1,1,0],[0,0,1],[1,0,0]],"state":"SOLVED","solver":"Pending"},{"id":157,"coords":[[0,0,0],[0,0,-1],[0,0,-2],[0,-1,-1],[0,0,1],[0,1,1],[-1,0,1],[1,0,0]],"state":"SOLVED","solver":"Charles-Émile Fecteau","verifiers":["Justin Maddux","Max Roy","Jonas Schöne"]},{"id":158,"coords":[[0,0,0],[0,0,-1],[0,-1,-1],[0,-1,-2],[0,1,-1],[0,0,1],[-1,0,1],[1,0,1]],"state":"SOLVED","solver":"Pending"},{"id":159,"coords":[[0,0,0],[0,0,-1],[0,0,-2],[0,0,-3],[0,-1,0],[-1,-1,0],[-2,-1,0],[1,0,0]],"state":"SOLVED","solver":"Sullivan Figurskey","verifiers":["Matt Parker","Daan Rijnkels","Jose Antonio Gonzalez"]},{"id":160,"coords":[[0,0,0],[0,0,-1],[0,-1,-1],[0,-1,-2],[-1,-1,-1],[0,1,0],[0,1,1],[1,1,0]],"state":"SOLVED","solver":"Sullivan Figurskey","verifiers":["Daan Rijnkels","John Sawyer","Asher Margulies"]},{"id":161,"coords":[[0,0,0],[0,0,-1],[0,0,-2],[0,-1,-2],[0,1,0],[0,1,1],[-1,1,0],[1,1,0]],"state":"SOLVED","solver":"Caleb Kavaloff","verifiers":["Simon E.M.","Frankie Mercado","Lucas Emanuel Genova"]},{"id":162,"coords":[[0,0,0],[0,0,-1],[0,-1,-1],[0,-2,-1],[-1,0,-1],[0,1,0],[0,2,0],[1,1,0]],"state":"SOLVED","solver":"Jim Andress","verifiers":["Rick Rijpers","Oke Petersen","John-Luca Feindt"]},{"id":163,"coords":[[0,0,0],[0,0,-1],[0,-1,-1],[-1,0,-1],[0,1,0],[0,2,0],[0,0,1],[1,0,0]],"state":"SOLVED","solver":"Michael Nebesny","verifiers":["Jason Wang","Eddie Heyne","KaasGrater"]},{"id":164,"coords":[[0,0,0],[0,0,-1],[0,0,-2],[0,-1,-2],[0,1,0],[-1,1,0],[-1,1,1],[1,0,0]],"state":"SOLVED","solver":"Jacob Stern","verifiers":["Paulio","David P. Kruger","Michael Gregory Baska"]},{"id":165,"coords":[[0,0,0],[0,0,-1],[0,0,-2],[0,-1,-2],[-1,0,-1],[1,0,0],[1,0,1],[0,1,0]],"state":"SOLVED","solver":"Valentin Jestl","verifiers":["Seth Harwood","r10pez10","Daniel Herrera"]},{"id":166,"coords":[[0,0,0],[0,0,-1],[0,0,-2],[0,-1,-1],[-1,0,0],[-1,0,1],[-1,1,0],[1,0,0]],"state":"SOLVED","solver":"Andrew Brooks","verifiers":["Daniel Busse","Sven Neumann","Tillmann Sliwinski"]},{"id":167,"coords":[[0,0,0],[0,0,-1],[0,-1,-1],[-1,0,-1],[0,1,0],[0,2,0],[0,0,1],[1,0,1]],"state":"SOLVED","solver":"Benjamin Zielinski","verifiers":["Noah Jerry Boekweg","Louis Davies","Shaylene"]},{"id":168,"coords":[[0,0,0],[0,0,-1],[0,0,-2],[0,-1,-2],[0,0,1],[-1,0,1],[1,0,1],[0,1,0]],"state":"SOLVED","solver":"Pending"},{"id":169,"coords":[[0,0,0],[0,0,-1],[0,0,-2],[0,-1,-2],[0,1,-2],[-1,0,0],[-1,0,1],[-1,0,2]],"state":"SOLVED","solver":"Sean Wheeldon","verifiers":["Frank Steffahn","Eddie Heyne","Metin Suloglu"]},{"id":170,"coords":[[0,0,0],[0,0,-1],[0,-1,-1],[0,-1,-2],[0,0,1],[0,1,1],[-1,0,0],[1,0,0]],"state":"SOLVED","solver":"Yannic Kugler","verifiers":["Jason Wang","Konrad Pitt","Jacob Glover"]},{"id":171,"coords":[[0,0,0],[0,0,-1],[0,0,-2],[0,-1,-2],[-1,0,-2],[0,1,0],[0,1,1],[1,1,0]],"state":"SOLVED","solver":"Thomas, Noelle, and Brett","verifiers":["Pranav Ramamurthy","Kevin Gomez","John Armstrong"]},{"id":172,"coords":[[0,0,0],[0,0,-1],[0,0,-2],[0,-1,-1],[-1,0,0],[-1,0,1],[1,0,0],[1,1,0]],"state":"SOLVED","solver":"Grove DeGroof","verifiers":["ellena davoine","John Pearce","Saul Roche"]},{"id":173,"coords":[[0,0,0],[0,0,-1],[0,-1,-1],[-1,-1,-1],[0,1,0],[0,2,0],[1,0,0],[1,0,1]],"state":"SOLVED","solver":"Valentin Jestl","verifiers":["Paul Dequidt","Charlie Brady","Rick Rijpers"]},{"id":174,"coords":[[0,0,0],[0,0,-1],[0,-1,-1],[0,-1,-2],[-1,0,-1],[1,0,0],[1,0,1],[1,1,1]],"state":"SOLVED","solver":"Simão da Graça Marto","verifiers":["Devin Danko","Jesper Appelberg","Max Roy"]},{"id":175,"coords":[[0,0,0],[0,0,-1],[0,-1,-1],[-1,-1,-1],[0,1,0],[0,2,0],[0,0,1],[1,0,0]],"state":"SOLVED","solver":"Julian Koch","verifiers":["Koen Timmermans","Simon Marynissen","Ivan Navarro"]},{"id":176,"coords":[[0,0,0],[0,0,-1],[0,-1,-1],[0,-2,-1],[-1,-1,-1],[0,1,0],[1,1,0],[1,2,0]],"state":"SOLVED","solver":"Alex Whitaker","verifiers":["Luis Fernando Lara Madrid","Paul Dequidt","SeaLove"]},{"id":177,"coords":[[0,0,0],[0,0,-1],[0,-1,-1],[0,1,-1],[-1,0,0],[-2,0,0],[0,0,1],[1,0,0]],"state":"SOLVED","solver":"Jordyn Hyde","verifiers":["Shane Gleeson","Benjamin Swart","Jackson Kilger"]},{"id":178,"coords":[[0,0,0],[0,0,-1],[0,-1,-1],[-1,-1,-1],[-1,-1,-2],[0,1,0],[1,1,0],[1,1,1]],"state":"SOLVED","solver":"Marko Srpak","verifiers":["Neil Sullivan","Kenneth Harold Johnson","Cyrus Carlson"]},{"id":179,"coords":[[0,0,0],[0,0,-1],[0,-1,-1],[0,-2,-1],[-1,0,-1],[1,0,0],[2,0,0],[0,1,0]],"state":"SOLVED","solver":"Lode Vandevenne","verifiers":["Zakir","Aleš Chudárek","Jasper Vrolijk"]},{"id":180,"coords":[[0,0,0],[0,0,-1],[0,-1,-1],[0,-2,-1],[0,0,-2],[-1,0,0],[-1,1,0],[-1,2,0]],"state":"SOLVED","solver":"Pending"},{"id":181,"coords":[[0,0,0],[0,0,-1],[0,-1,-1],[0,-1,-2],[-1,-1,-1],[0,0,1],[1,0,1],[1,1,1]],"state":"SOLVED","solver":"Gavin O’Malley","verifiers":["Matt Parker","Pieter van Zoelen","Michael Gregory Baska"]},{"id":182,"coords":[[0,0,0],[0,0,-1],[0,-1,-1],[0,-2,-1],[-1,0,0],[-2,0,0],[-1,1,0],[1,0,0]],"state":"SOLVED","solver":"Beau Schellekens","verifiers":["Noah Jerry Boekweg","Jan Nienhaus","Anonymous"]},{"id":183,"coords":[[0,0,0],[0,0,-1],[0,0,-2],[0,-1,-2],[-1,0,-1],[0,0,1],[0,1,1],[1,1,1]],"state":"SOLVED","solver":"James Fong","verifiers":["Oke Petersen","Peter Gagliardi","Edward Green"]},{"id":184,"coords":[[0,0,0],[0,0,-1],[0,0,-2],[0,-1,-2],[-1,-1,-2],[0,1,0],[1,1,0],[1,1,1]],"state":"SOLVED","solver":"Xavier Lamphere","verifiers":["Simon E.M.","Anhadvir Singh","P. Imre"]},{"id":185,"coords":[[0,0,0],[0,0,-1],[0,-1,-1],[-1,-1,-1],[0,1,0],[0,2,0],[1,1,0],[0,0,1]],"state":"SOLVED","solver":"Kewin Ignasiak","verifiers":["Jeppe Jon Holt","Julian Ahl","Anhadvir Singh"]},{"id":186,"coords":[[0,0,0],[0,0,-1],[0,-1,-1],[0,-1,-2],[-1,0,0],[-1,1,0],[-1,2,0],[0,0,1]],"state":"SOLVED","solver":"August Asp (Spu7Nix)","verifiers":["r10pez10","Alexander Liddington","Adrien"]},{"id":187,"coords":[[0,0,0],[0,0,-1],[0,0,-2],[0,-1,-2],[0,0,1],[-1,0,1],[1,0,0],[1,1,0]],"state":"SOLVED","solver":"Daniel Yuan","verifiers":["William R. Wilkins","Marcos Petri","Croma"]},{"id":188,"coords":[[0,0,0],[0,0,-1],[0,0,-2],[0,-1,-1],[0,0,1],[-1,0,1],[1,0,0],[1,1,0]],"state":"SOLVED","solver":"Ethan Woll","verifiers":["Nathanael Ramirez","Kieran Hingston","Jan Nienhaus"]},{"id":189,"coords":[[0,0,0],[0,0,-1],[0,-1,-1],[0,-1,-2],[-1,-1,-2],[0,1,0],[1,1,0],[1,1,1]],"state":"SOLVED","solver":"Simon Klein","verifiers":["valentin comte","Revi Gerner","Jack Rickard"]},{"id":190,"coords":[[0,0,0],[0,0,-1],[0,-1,-1],[0,-1,-2],[-1,0,-1],[0,0,1],[1,0,1],[1,1,1]],"state":"SOLVED","solver":"Lukas Klawuhn","verifiers":["Daniel Yuan","ErikB","Fernando Gaete"]},{"id":191,"coords":[[0,0,0],[0,0,-1],[0,-1,-1],[0,-1,-2],[0,0,1],[0,1,1],[-1,0,1],[1,0,1]],"state":"SOLVED","solver":"Herman Lauenstein","verifiers":["Lukas Baier","Garrison Burger","Leonardo Caetano Gomide"]},{"id":192,"coords":[[0,0,0],[0,0,-1],[0,0,-2],[0,-1,0],[-1,-1,0],[1,0,0],[1,1,0],[0,0,1]],"state":"SOLVED","solver":"gauvain lefort","verifiers":["Saul Roche","Andre Leue","John-Luca Feindt"]},{"id":193,"coords":[[0,0,0],[0,0,-1],[0,0,-2],[0,0,-3],[0,-1,0],[-1,-1,0],[0,1,0],[1,1,0]],"state":"SOLVED","solver":"Pending"},{"id":194,"coords":[[0,0,0],[0,0,-1],[0,-1,-1],[-1,-1,-1],[-1,-2,-1],[0,1,0],[1,1,0],[1,2,0]],"state":"SOLVED","solver":"Felipe Jannarone","verifiers":["John Pearce","Aki Cabrera","Luke Stenger"]},{"id":195,"coords":[[0,0,0],[0,0,-1],[0,0,-2],[0,0,-3],[0,-1,-1],[-1,0,0],[-1,1,0],[1,0,0]],"state":"SOLVED","solver":"Hunter McLinn","verifiers":["Joseph Klopchic","Kevin Gomez","Dylan Hendrickson"]},{"id":196,"coords":[[0,0,0],[0,0,-1],[0,0,-2],[0,-1,-2],[-1,0,-1],[0,1,0],[0,1,1],[1,1,0]],"state":"SOLVED","solver":"Wilmer Lundell","verifiers":["r10pez10","Caleb Lehman","Pavel Rozhkov"]},{"id":197,"coords":[[0,0,0],[0,0,-1],[0,-1,-1],[0,-2,-1],[-1,0,-1],[0,1,0],[0,2,0],[1,2,0]],"state":"SOLVED","solver":"Jim Andress","verifiers":["Sullivan Figurskey","Alban VACHETTE","Eric Rodriguez"]},{"id":198,"coords":[[0,0,0],[0,0,-1],[0,-1,-1],[0,-1,-2],[0,1,0],[0,1,1],[-1,0,0],[1,0,0]],"state":"SOLVED","solver":"Sid Miller","verifiers":["Jonas Jahnel","Henrique Campos Navas","Kenneth Harold Johnson"]},{"id":199,"coords":[[0,0,0],[0,0,-1],[0,0,-2],[0,-1,-1],[0,0,1],[-1,0,1],[0,1,0],[1,1,0]],"state":"SOLVED","solver":"Pending"},{"id":200,"coords":[[0,0,0],[0,0,-1],[0,-1,-1],[-1,-1,-1],[0,0,1],[0,0,2],[1,0,1],[0,1,0]],"state":"SOLVED","solver":"Pending"},{"id":201,"coords":[[0,0,0],[0,0,-1],[0,0,-2],[0,-1,-2],[0,1,-1],[-1,0,0],[-1,0,1],[-1,0,2]],"state":"SOLVED","solver":"Oscar Baglivio","verifiers":["EbbDrop","Robbe Pincket","Edmund Harriss"]},{"id":202,"coords":[[0,0,0],[0,0,-1],[0,0,-2],[0,0,-3],[0,-1,0],[-1,-1,0],[0,1,0],[1,0,0]],"state":"SOLVED","solver":"Garrick Glickenhouse","verifiers":["Rick Rijpers","Lucas P.","Mauro Bampo"]},{"id":203,"coords":[[0,0,0],[0,0,-1],[0,-1,-1],[0,-1,-2],[0,1,0],[-1,1,0],[0,0,1],[1,0,0]],"state":"SOLVED","solver":"Dylan Hale","verifiers":["Oriol Panadès Closes","Garrett Gularson","Feliks"]},{"id":204,"coords":[[0,0,0],[0,0,-1],[0,0,-2],[0,-1,-2],[0,1,-1],[0,0,1],[-1,0,1],[1,0,1]],"state":"SOLVED","solver":"Pending"},{"id":205,"coords":[[0,0,0],[0,0,-1],[0,0,-2],[0,-1,-2],[-1,0,-1],[0,0,1],[1,0,1],[1,1,1]],"state":"SOLVED","solver":"Jay McArthur","verifiers":["Gabriel Leo Denney-Martell","Maxim Brückmann","Seth Harwood"]},{"id":206,"coords":[[0,0,0],[0,0,-1],[0,0,-2],[0,-1,-2],[-1,0,-1],[0,1,0],[1,1,0],[1,1,1]],"state":"SOLVED","solver":"Zeus2459","verifiers":["EbbDrop","Jack Rickard","José Sousa"]},{"id":207,"coords":[[0,0,0],[0,0,-1],[0,0,-2],[0,-1,-2],[0,0,1],[-1,0,1],[0,1,0],[1,0,0]],"state":"SOLVED","solver":"Pending"},{"id":208,"coords":[[0,0,0],[0,0,-1],[0,0,-2],[0,-1,-2],[-1,0,0],[-1,0,1],[-1,1,1],[1,0,0]],"state":"SOLVED","solver":"Pending"},{"id":209,"coords":[[0,0,0],[0,0,-1],[0,-1,-1],[0,-1,-2],[-1,0,0],[-1,0,1],[-1,1,0],[1,0,0]],"state":"SOLVED","solver":"Sniperian","verifiers":["Julian Ahl","Morris Jones","YellowBunny"]},{"id":210,"coords":[[0,0,0],[0,0,-1],[0,0,-2],[0,-1,-1],[0,0,1],[0,1,1],[-1,0,0],[1,0,0]],"state":"SOLVED","solver":"Nicholas Pickett","verifiers":["Daan Rijnkels","Nick Guo","Robbe Pincket"]},{"id":211,"coords":[[0,0,0],[0,0,-1],[0,0,-2],[0,0,-3],[0,-1,-1],[0,1,0],[-1,1,0],[1,0,0]],"state":"SOLVED","solver":"JT Perek","verifiers":["Ezra Guerrero","dadalev","Michael Tardibuono"]},{"id":212,"coords":[[0,0,0],[0,0,-1],[0,-1,-1],[-1,-1,-1],[0,0,-2],[1,0,0],[1,0,1],[1,1,0]],"state":"SOLVED","solver":"Jacob Stern","verifiers":["Daan Rijnkels","Mariusz","Nathan Nelson"]},{"id":213,"coords":[[0,0,0],[0,0,-1],[0,0,-2],[0,0,1],[0,-1,0],[0,1,0],[-1,0,0],[1,0,0]],"state":"SOLVED","solver":"Giovanna Diaz and Joseph O'Rourke","verifiers":[]},{"id":214,"coords":[[0,0,0],[0,0,-1],[0,-1,-1],[-1,-1,-1],[0,0,-2],[0,1,0],[1,1,0],[1,1,1]],"state":"SOLVED","solver":"Pending"},{"id":215,"coords":[[0,0,0],[0,0,-1],[0,0,-2],[0,-1,0],[-1,-1,0],[0,0,1],[0,1,0],[1,0,0]],"state":"SOLVED","solver":"Elliott Sampson","verifiers":["kilian zepf","Finn Tredget","Zakir"]},{"id":216,"coords":[[0,0,0],[0,0,-1],[0,-1,-1],[-1,-1,-1],[0,0,1],[0,0,2],[0,1,1],[1,0,1]],"state":"SOLVED","solver":"Pending"},{"id":217,"coords":[[0,0,0],[0,0,-1],[0,0,-2],[0,0,1],[0,-1,1],[-1,0,0],[-1,1,0],[1,0,0]],"state":"SOLVED","solver":"Rick Rijpers","verifiers":["Jeroen Meringa","Matthew Miller","Jack Rickard"]},{"id":218,"coords":[[0,0,0],[0,0,-1],[0,-1,-1],[-1,-1,-1],[0,0,1],[0,0,2],[1,0,0],[1,1,0]],"state":"SOLVED","solver":"Tamás Makai","verifiers":["Ryan Bailey","Alexander Martin Wagner","Oke Petersen"]},{"id":219,"coords":[[0,0,0],[0,0,-1],[0,-1,-1],[-1,-1,-1],[-1,-2,-1],[1,0,0],[1,1,0],[2,1,0]],"state":"SOLVED","solver":"Pending"},{"id":220,"coords":[[0,0,0],[0,0,-1],[0,-1,-1],[-1,-1,-1],[1,-1,-1],[0,0,1],[0,0,2],[0,1,2]],"state":"SOLVED","solver":"Pending"},{"id":221,"coords":[[0,0,0],[0,0,-1],[0,-1,-1],[0,-2,-1],[-1,0,0],[-2,0,0],[1,0,0],[1,1,0]],"state":"SOLVED","solver":"Michael Parkinson","verifiers":["Joseph","Saul Roche","Gustavo Tontini"]},{"id":222,"coords":[[0,0,0],[0,0,-1],[0,-1,-1],[0,1,-1],[-1,0,-1],[0,0,1],[0,0,2],[1,0,1]],"state":"SOLVED","solver":"Algot Lindestam","verifiers":["Marcos Petri","Metin Suloglu","Artemis Gardner"]},{"id":223,"coords":[[0,0,0],[0,0,-1],[0,-1,-1],[0,-2,-1],[-1,0,0],[-2,0,0],[0,1,0],[1,1,0]],"state":"SOLVED","solver":"Michael Parkinson","verifiers":["Eddie Heyne","Luis Novoa","Seth Harwood"]},{"id":224,"coords":[[0,0,0],[0,0,-1],[0,-1,-1],[0,-1,-2],[-1,0,-1],[0,1,0],[0,1,1],[1,0,0]],"state":"SOLVED","solver":"Luke Stenger","verifiers":["Jordyn Hyde","Michael MacDonald","Roman Berens"]},{"id":225,"coords":[[0,0,0],[0,0,-1],[0,0,-2],[0,-1,-2],[0,1,0],[-1,1,0],[1,1,0],[0,0,1]],"state":"SOLVED","solver":"Yves Kompis","verifiers":["Elise Baczek","Georgios Papoutsis","Kaustubh Rakhade"]},{"id":226,"coords":[[0,0,0],[0,0,-1],[0,-1,-1],[0,-1,-2],[-1,0,0],[-1,0,1],[0,1,0],[1,1,0]],"state":"SOLVED","solver":"Adam Nielson","verifiers":["Daniel Herrera","Mees Broer","Illya Kierkosz"]},{"id":227,"coords":[[0,0,0],[0,0,-1],[0,-1,-1],[-1,-1,-1],[1,-1,-1],[0,1,0],[0,1,1],[0,2,1]],"state":"SOLVED","solver":"Neil Sullivan","verifiers":["John Lewis","John Pearce","Robbie Tavener"]},{"id":228,"coords":[[0,0,0],[0,0,-1],[0,-1,-1],[0,-1,-2],[-1,0,-1],[0,1,0],[0,1,1],[1,1,0]],"state":"SOLVED","solver":"Pending"},{"id":229,"coords":[[0,0,0],[0,0,-1],[0,-1,-1],[-1,-1,-1],[1,0,0],[2,0,0],[0,1,0],[0,1,1]],"state":"SOLVED","solver":"Pending"},{"id":230,"coords":[[0,0,0],[0,0,-1],[0,-1,-1],[0,-2,-1],[-1,-1,-1],[1,0,0],[2,0,0],[1,1,0]],"state":"SOLVED","solver":"Michael Parkinson","verifiers":["Roy Boggs","Daniel Jonathan Sherman","Marco"]},{"id":231,"coords":[[0,0,0],[0,0,-1],[0,-1,-1],[0,-2,-1],[-1,0,0],[-2,0,0],[0,1,0],[1,0,0]],"state":"SOLVED","solver":"Michael Parkinson","verifiers":["Jacobo","GwynBleidD","Louis Davies"]},{"id":232,"coords":[[0,0,0],[0,0,-1],[0,0,-2],[0,-1,-2],[-1,0,0],[-1,1,0],[-1,2,0],[0,0,1]],"state":"SOLVED","solver":"David F","verifiers":["Sourish Sharma","Paolo","Adam Spanel"]},{"id":233,"coords":[[0,0,0],[0,0,-1],[0,0,-2],[0,0,-3],[0,-1,-1],[-1,0,0],[-1,1,0],[-1,2,0]],"state":"SOLVED","solver":"Pending"},{"id":234,"coords":[[0,0,0],[0,0,-1],[0,0,-2],[0,-1,-1],[0,0,1],[-1,0,1],[0,1,0],[1,0,0]],"state":"SOLVED","solver":"Alex Neufeld","verifiers":["Caleb Kavaloff","Pegenau","John Sawyer"]},{"id":235,"coords":[[0,0,0],[0,0,-1],[0,0,-2],[0,-1,-2],[-1,0,0],[-1,1,0],[0,0,1],[1,0,0]],"state":"SOLVED","solver":"Pending"},{"id":236,"coords":[[0,0,0],[0,0,-1],[0,0,-2],[0,-1,-2],[-1,0,-2],[0,0,1],[0,1,1],[1,1,1]],"state":"SOLVED","solver":"Sean Wheeldon","verifiers":["Charles-Émile Fecteau","T-Jay_HD","Tim Rexrodt"]},{"id":237,"coords":[[0,0,0],[0,0,-1],[0,0,-2],[0,-1,-1],[-1,0,-1],[0,0,1],[0,1,1],[1,0,0]],"state":"SOLVED","solver":"Esran Douma","verifiers":["Ryan Weisenburger","Bretton Hoover","Natalie"]},{"id":238,"coords":[[0,0,0],[0,0,-1],[0,-1,-1],[0,-1,-2],[0,1,-1],[-1,0,0],[-1,0,1],[-1,0,2]],"state":"SOLVED","solver":"Leonardo Caetano Gomide","verifiers":["Sébastien Chagnon","Ryan Bailey","Khodor"]},{"id":239,"coords":[[0,0,0],[0,0,-1],[0,0,-2],[0,-1,-2],[-1,0,0],[-1,0,1],[-1,0,2],[0,1,0]],"state":"SOLVED","solver":"Guillaume Sabbagh","verifiers":["Ryan Weisenburger","Niels Kouwenhoven","Petr Dymanus"]},{"id":240,"coords":[[0,0,0],[0,0,-1],[0,-1,-1],[-1,-1,-1],[0,0,-2],[0,1,0],[0,1,1],[1,1,0]],"state":"SOLVED","solver":"Kerry Haenftling","verifiers":["Brent Nelson","Simon E.M.","Sydney Stafferton"]},{"id":241,"coords":[[0,0,0],[0,0,-1],[0,0,-2],[0,-1,-1],[-1,0,-1],[0,0,1],[0,1,0],[1,0,0]],"state":"SOLVED","solver":"MathGuineaPig","verifiers":["Reed Pratt","Kevin Gomez","Ryan Weisenburger"]},{"id":242,"coords":[[0,0,0],[0,0,-1],[0,-1,-1],[0,-2,-1],[-1,-2,-1],[1,0,0],[2,0,0],[2,1,0]],"state":"SOLVED","solver":"Lode Vandevenne","verifiers":["Fernando Gaete","John Pearce","Simo S"]},{"id":243,"coords":[[0,0,0],[0,0,-1],[0,-1,-1],[-1,-1,-1],[-1,-2,-1],[1,0,0],[2,0,0],[2,1,0]],"state":"SOLVED","solver":"Lode Vandevenne","verifiers":["Marco","Antoine DOP","Simon Spurrell"]},{"id":244,"coords":[[0,0,0],[0,0,-1],[0,-1,-1],[0,-1,-2],[-1,-1,-1],[1,0,0],[1,0,1],[1,1,0]],"state":"SOLVED","solver":"Jim Andress","verifiers":["Mark Basham","Pegenau","Mariusz"]},{"id":245,"coords":[[0,0,0],[0,0,-1],[0,-1,-1],[-1,-1,-1],[1,0,0],[2,0,0],[1,0,1],[0,1,0]],"state":"SOLVED","solver":"Rhys Cahill","verifiers":["Devin Danko","Sullivan Figurskey","Rick Rijpers"]},{"id":246,"coords":[[0,0,0],[0,0,-1],[0,0,-2],[0,-1,-2],[-1,0,-2],[0,1,0],[1,1,0],[1,1,1]],"state":"SOLVED","solver":"Josh Ball","verifiers":["EbbDrop","Mark Jackson Pulver","Daniel Spurgeon"]},{"id":247,"coords":[[0,0,0],[0,0,-1],[0,0,-2],[0,-1,-2],[-1,-1,-2],[0,0,1],[1,0,1],[1,1,1]],"state":"SOLVED","solver":"Daan Rijnkels","verifiers":["Glenn Jenkins","Karim Maassen","UsrBinPRL"]},{"id":248,"coords":[[0,0,0],[0,0,-1],[0,-1,-1],[0,-1,-2],[-1,0,0],[-1,0,1],[-1,1,1],[1,0,0]],"state":"SOLVED","solver":"Oscar Harju","verifiers":["UsrBinPRL","Ernestas Olbert-Tolstov","James Macleod"]},{"id":249,"coords":[[0,0,0],[0,0,-1],[0,-1,-1],[-1,-1,-1],[-1,-1,-2],[1,0,0],[1,1,0],[1,1,1]],"state":"SOLVED","solver":"Matt Parker","verifiers":["Stuart Ward","Octavia Togami","Andrea Consonni"]},{"id":250,"coords":[[0,0,0],[0,0,-1],[0,0,-2],[0,-1,-2],[-1,0,0],[-1,0,1],[1,0,0],[1,1,0]],"state":"SOLVED","solver":"Markus Reher","verifiers":["Glenn Jenkins","Marco","Joseph"]},{"id":251,"coords":[[0,0,0],[0,0,-1],[0,0,-2],[0,-1,-2],[0,0,1],[0,1,1],[-1,0,1],[1,0,1]],"state":"SOLVED","solver":"Dmitriy Molostvov","verifiers":["Reed Pratt","Maya S","Andrew Raymond"]},{"id":252,"coords":[[0,0,0],[0,0,-1],[0,-1,-1],[0,-2,-1],[0,0,-2],[0,1,0],[-1,1,0],[1,1,0]],"state":"SOLVED","solver":"Justin Maddux","verifiers":["Jonas Jahnel","Alban VACHETTE","John Pearce"]},{"id":253,"coords":[[0,0,0],[0,0,-1],[0,-1,-1],[0,-1,-2],[0,1,-1],[-1,0,0],[-1,0,1],[1,0,0]],"state":"SOLVED","solver":"Pending"},{"id":254,"coords":[[0,0,0],[0,0,-1],[0,-1,-1],[0,-1,-2],[-1,-1,-1],[0,1,0],[1,1,0],[1,1,1]],"state":"SOLVED","solver":"Konrad Pitt","verifiers":["John Lewis","Daan Rijnkels","Jan Stüven"]},{"id":255,"coords":[[0,0,0],[0,0,-1],[0,0,-2],[0,-1,-1],[-1,0,-1],[0,1,0],[1,1,0],[0,0,1]],"state":"SOLVED","solver":"Oskar Goldhahn","verifiers":["Oriol Panadès Closes","Wilco Verhoef","Philip Peal"]},{"id":256,"coords":[[0,0,0],[0,0,-1],[0,0,-2],[0,-1,-2],[-1,0,-1],[1,0,0],[1,1,0],[1,1,1]],"state":"SOLVED","solver":"Ryan Froese","verifiers":["Matt Parker","Cyrus Carlson","TrampaQ"]},{"id":257,"coords":[[0,0,0],[0,0,-1],[0,-1,-1],[0,-1,-2],[-1,-1,-1],[1,0,0],[1,1,0],[1,1,1]],"state":"SOLVED","solver":"Pending"},{"id":258,"coords":[[0,0,0],[0,0,-1],[0,-1,-1],[-1,-1,-1],[1,0,-1],[0,1,0],[0,2,0],[0,1,1]],"state":"SOLVED","solver":"Alex Neufeld","verifiers":["Arsh Verma","Finlay M","Ellie Vallard"]},{"id":259,"coords":[[0,0,0],[0,0,-1],[0,0,-2],[0,-1,-1],[-1,0,0],[-1,0,1],[0,1,0],[1,0,0]],"state":"SOLVED","solver":"Manuel Josef Pfleger","verifiers":["Jamie Rogers","KaasGrater","Jonathan Dench"]},{"id":260,"coords":[[0,0,0],[0,0,-1],[0,-1,-1],[-1,-1,-1],[1,0,0],[2,0,0],[0,0,1],[0,1,1]],"state":"SOLVED","solver":"Adrian Martinez Morcillo","verifiers":["Jonathan Burgess","Marco Scholten","Garrett Gularson"]},{"id":261,"coords":[[0,0,0],[0,0,-1],[0,0,-2],[0,-1,-1],[0,1,0],[-1,1,0],[0,0,1],[1,0,0]],"state":"SOLVED","solver":"Eduard Volf","verifiers":["Seth Harwood","Devin Danko","Ryan Taylor"]}]}